BayesASE/__init__.py
BayesASE/data/__init__.py
BayesASE/data/environmentalmodel2.stan
BayesASE/data/nbmodel_stan2_flex_prior.R
BayesASE-21.1.13.1.data/scripts/bwa_split_sam_seonly_2output.py
BayesASE-21.1.13.1.data/scripts/calculate_priors_ase_count_tables.py
BayesASE-21.1.13.1.data/scripts/check_aln_design_file.py
BayesASE-21.1.13.1.data/scripts/check_comparate_design_file.py
BayesASE-21.1.13.1.data/scripts/check_lost_reads.py
BayesASE-21.1.13.1.data/scripts/check_sam_present.py
BayesASE-21.1.13.1.data/scripts/check_samcomp_lost_reads.py
BayesASE-21.1.13.1.data/scripts/combine_count_tables.py
BayesASE-21.1.13.1.data/scripts/gen_headers_after_merge_priors_one_comparate.py
BayesASE-21.1.13.1.data/scripts/merge_comparates_generate_bayesian_headers.py
BayesASE-21.1.13.1.data/scripts/merge_priors_to_comparate.py
BayesASE-21.1.13.1.data/scripts/nbmodel_stan2.py
BayesASE-21.1.13.1.data/scripts/sam_compare_w_feature.py
BayesASE-21.1.13.1.data/scripts/summarize_sam_compare_cnts_table_1cond.py
BayesASE-21.1.13.1.dist-info/METADATA
BayesASE-21.1.13.1.dist-info/WHEEL
BayesASE-21.1.13.1.dist-info/top_level.txt
BayesASE-21.1.13.1.dist-info/RECORD
