Metadata-Version: 2.1
Name: BayesASE
Version: 21.1.13.1
Summary: Bayesian analysis of allele specific expression
Home-page: https://github.com/McIntyre-Lab/BayesASE
Author: McIntyre Lab, Universify of Florida
Author-email: om@rc.ufl.edu
License: MIT
Keywords: bayesian allele expression
Platform: any
Classifier: Development Status :: 4 - Beta
Classifier: Environment :: Console
Classifier: Intended Audience :: Science/Research
Classifier: Operating System :: OS Independent
Classifier: License :: OSI Approved :: MIT License
Classifier: Programming Language :: Python :: 3
Classifier: Topic :: Scientific/Engineering
Classifier: Topic :: Scientific/Engineering :: Bio-Informatics
Requires-Python: >=3.6
Requires-Dist: biopython (>=1.70)
Requires-Dist: numpy (>=1.18.1)
Requires-Dist: pandas (>=1.0.3)
Requires-Dist: importlib-resources ; python_version < "3.7.0"
